Workbook

Sheet VAT Calculator
A1: AEC | MULTI-REGION VAT CALCULATOR
A2: AFRIQUEEUROPECONNEXIONVMETC · Kraków · Douala · Abuja
A4: 🇵🇱 POLAND — JPK V7 VAT | E4: 🌍 OHADA — Cameroon / CEMAC VAT
A5: Net Amount (PLN) | B5: 1000 | E5: Net Amount (XAF) | F5: 500000
A6: VAT Rate | B6: 0.23 | E6: VAT Rate | F6: 0.1925
A7: VAT Amount | B7: =B5*B6 -> 230 | E7: VAT Amount | F7: =F5*F6 -> 96250
A8: Gross Amount | B8: =B5+B7 -> 1230 | E8: Gross Amount | F8: =F5+F7 -> 596250
A9: Poland VAT Rate Reference | E9: OHADA Rate Reference
A10: Standard (23%) | B10: 0.23 | C10: → Enter in B6 | E10: Standard (19.25%) | F10: 0.1925
A11: Reduced (8%) | B11: 0.08 | C11: → Enter in B6 | E11: Tourism (11.11%) | F11: 0.1111
A12: Super-reduced (5%) | B12: 0.05 | C12: → Enter in B6 | E12: Exempt (0%) | F12: 0
A13: Zero (0%) | B13: 0 | C13: → Enter in B6
A15: 🇳🇬 NIGERIA — FIRS VAT (VAITA 2019, 7.5%) | E15: 🇪🇺 EU — GENERAL VAT CALCULATOR
A16: Net Amount (NGN) | B16: 200000 | C16: Nigeria FIRS VAT = 7.5% VAITA 2019 rate. Basic food, medical, educational services are exempt. File monthly via FIRS e-Services. | E16: Net Amount (EUR) | F16: 5000
A17: VAT Rate | B17: 0.075 | E17: VAT Rate | F17: 0.2
A18: VAT Amount | B18: =B16*B17 -> 15000 | E18: VAT Amount | F18: =F16*F17 -> 1000
A19: Gross Amount | B19: =B16+B18 -> 215000 | E19: Gross Amount | F19: =F16+F18 -> 6000
E20: EU Country Reference Rates
E21: Germany 19% | F21: 0.19
E22: France 20% | F22: 0.2
E23: Italy 22% | F23: 0.22
E24: Belgium 21% | F24: 0.21
A26: 💱 CURRENCY QUICK CONVERTER (update blue rate cells weekly)
A27: Currency | B27: Amount | C27: → EUR | D27: → PLN | E27: → XAF | F27: → NGN | G27: EUR Result | H27: PLN Result
A28: EUR | B28: 1000 | C28: 1 | D28: 4.28 | E28: 655.96 | F28: 1580 | G28: =B28*C28 -> 1000 | H28: =B28*D28 -> 4280
A29: PLN | B29: 1000 | C29: 0.2336 | D29: 1 | E29: 153.27 | F29: 369 | G29: =B29*C29 -> 233.6 | H29: =B29*D29 -> 1000
A30: XAF | B30: 50000 | C30: 0.00152 | D30: 0.00652 | E30: 1 | F30: 2.41 | G30: =B30*C30 -> 76 | H30: =B30*D30 -> 326
A31: NGN | B31: 500000 | C31: 0.00063 | D31: 0.00271 | E31: 0.415 | F31: 1 | G31: =B31*C31 -> 315 | H31: =B31*D31 -> 1355
A33: ℹ BLUE cells = editable inputs | BLACK cells = auto-calculated | Update currency rates from ECB / FIRS / BEAC official sources

Sheet Expense Tracker
A1: AEC | BUSINESS EXPENSE TRACKER
A2: AFRIQUEEUROPECONNEXIONVMETC — Monthly Business Expense Log
A4: MONTHLY SUMMARY (auto-updates from entries below)
A5: TOTALS → | B5: Total Net | C5: Total VAT | D5: Total Gross | E5: Travel | F5: Software/IT | G5: Consulting | H5: Other | I5: Monthly Budget | J5: Variance
B6: =IFERROR(SUM(F12:F500),0) -> 205450 | C6: =IFERROR(SUM(G12:G500),0) -> 0.7325 | D6: =IFERROR(SUM(H12:H500),0) -> 244839.5 | E6: =IFERROR(SUMIF(C12:C500,"Travel",H12:H500),0) -> 1296 | F6: =IFERROR(SUMIF(C12:C500,"Software/IT",H12:H500),0) -> 553.5 | G6: =IFERROR(SUMIF(C12:C500,"Consulting",H12:H500),0) -> 3690 | H6: =IFERROR(D6-E6-F6-G6,0) -> 239300 | I6: 10000 | J6: =IFERROR(I6-D6,0) -> -234839.5
A10: EXPENSE ENTRIES — enter data in blue rows below
A11: # | B11: Date | C11: Category | D11: Vendor / Supplier | E11: Country | F11: Net Amount | G11: VAT % | H11: Gross Amount | I11: Description | J11: Receipt?
A12: 1 | B12: 2025-01-05 | C12: Travel | D12: LOT Polish Airlines | E12: Poland | F12: 1200 | G12: 0.08 | H12: =IFERROR(F12*(1+G12),0) -> 1296 | I12: Sample — Travel | J12: Yes
A13: 2 | B13: 2025-01-08 | C13: Software/IT | D13: Microsoft Azure | E13: Poland | F13: 450 | G13: 0.23 | H13: =IFERROR(F13*(1+G13),0) -> 553.5 | I13: Sample — Software/IT | J13: Yes
A14: 3 | B14: 2025-01-12 | C14: Consulting | D14: Legal Advisory Sp. | E14: Poland | F14: 3000 | G14: 0.23 | H14: =IFERROR(F14*(1+G14),0) -> 3690 | I14: Sample — Consulting | J14: Yes
A15: 4 | B15: 2025-01-15 | C15: Marketing | D15: Google Ads | E15: Other | F15: 800 | G15: 0 | H15: =IFERROR(F15*(1+G15),0) -> 800 | I15: Sample — Marketing | J15: Yes
A16: 5 | B16: 2025-01-20 | C16: Tax & Compliance | D16: OHADA Filing | E16: Cameroon | F16: 200000 | G16: 0.1925 | H16: =IFERROR(F16*(1+G16),0) -> 238500 | I16: Sample — Tax & Compliance | J16: Yes
A17: 6 | H17: =IFERROR(IF(F17="","",F17*(1+G17)),"")
A18: 7 | H18: =IFERROR(IF(F18="","",F18*(1+G18)),"")
A19: 8 | H19: =IFERROR(IF(F19="","",F19*(1+G19)),"")
A20: 9 | H20: =IFERROR(IF(F20="","",F20*(1+G20)),"")
A21: 10 | H21: =IFERROR(IF(F21="","",F21*(1+G21)),"")
A22: 11 | H22: =IFERROR(IF(F22="","",F22*(1+G22)),"")
A23: 12 | H23: =IFERROR(IF(F23="","",F23*(1+G23)),"")
A24: 13 | H24: =IFERROR(IF(F24="","",F24*(1+G24)),"")
A25: 14 | H25: =IFERROR(IF(F25="","",F25*(1+G25)),"")
A26: 15 | H26: =IFERROR(IF(F26="","",F26*(1+G26)),"")
A27: 16 | H27: =IFERROR(IF(F27="","",F27*(1+G27)),"")
A28: 17 | H28: =IFERROR(IF(F28="","",F28*(1+G28)),"")
... A100: 89 | H100: =IFERROR(IF(F100="","",F100*(1+G100)),"")

Sheet Dashboard
A1: AEC | EXPENSE DASHBOARD
A2: Auto-updated — all data pulls from Expense Tracker sheet
A4: KEY PERFORMANCE INDICATORS
B5: Total Gross Spend | C5: Total VAT | D5: Net Spend | E5: Monthly Budget | F5: Budget Remaining | G5: Travel Costs | H5: Software / IT
B6: ='Expense Tracker'!D6 -> 244839.5 | C6: ='Expense Tracker'!C6 -> 0.7325 | D6: ='Expense Tracker'!B6 -> 205450 | E6: ='Expense Tracker'!I6 -> 10000 | F6: ='Expense Tracker'!J6 -> -234839.5 | G6: ='Expense Tracker'!E6 -> 1296 | H6: ='Expense Tracker'!F6 -> 553.5
A9: SPEND BY CATEGORY | E9: SPEND BY COUNTRY
A10: Travel | B10: =IFERROR(SUMIF('Expense Tracker'!C12:C500,A10,'Expense Tracker'!H12:H500),0) -> 1296 | C10: =IFERROR(B10/'Expense Tracker'!D6,0) -> 0.0052932635 | E10: Poland | F10: =IFERROR(SUMIF('Expense Tracker'!E12:E500,E10,'Expense Tracker'!H12:H500),0) -> 5539.5 | G10: =IFERROR(F10/'Expense Tracker'!D6,0) -> 0.022625026
A11: Software/IT | B11: =IFERROR(SUMIF('Expense Tracker'!C12:C500,A11,'Expense Tracker'!H12:H500),0) -> 553.5 | C11: =IFERROR(B11/'Expense Tracker'!D6,0) -> 0.0022606646 | E11: Cameroon | F11: =IFERROR(SUMIF('Expense Tracker'!E12:E500,E11,'Expense Tracker'!H12:H500),0) -> 238500 | G11: =IFERROR(F11/'Expense Tracker'!D6,0) -> 0.97410753
A12: Consulting | B12: =IFERROR(SUMIF('Expense Tracker'!C12:C500,A12,'Expense Tracker'!H12:H500),0) -> 3690 | C12: =IFERROR(B12/'Expense Tracker'!D6,0) -> 0.015071098 | E12: Nigeria | F12: =IFERROR(SUMIF('Expense Tracker'!E12:E500,E12,'Expense Tracker'!H12:H500),0) -> 0 | G12: =IFERROR(F12/'Expense Tracker'!D6,0) -> 0
A13: Marketing | B13: =IFERROR(SUMIF('Expense Tracker'!C12:C500,A13,'Expense Tracker'!H12:H500),0) -> 800 | C13: =IFERROR(B13/'Expense Tracker'!D6,0) -> 0.0032674466 | E13: France | F13: =IFERROR(SUMIF('Expense Tracker'!E12:E500,E13,'Expense Tracker'!H12:H500),0) -> 0 | G13: =IFERROR(F13/'Expense Tracker'!D6,0) -> 0
A14: Payroll | B14: =IFERROR(SUMIF('Expense Tracker'!C12:C500,A14,'Expense Tracker'!H12:H500),0) -> 0 | C14: =IFERROR(B14/'Expense Tracker'!D6,0) -> 0 | E14: Germany | F14: =IFERROR(SUMIF('Expense Tracker'!E12:E500,E14,'Expense Tracker'!H12:H500),0) -> 0 | G14: =IFERROR(F14/'Expense Tracker'!D6,0) -> 0
A15: Rent/Utilities | B15: =IFERROR(SUMIF('Expense Tracker'!C12:C500,A15,'Expense Tracker'!H12:H500),0) -> 0 | C15: =IFERROR(B15/'Expense Tracker'!D6,0) -> 0 | E15: Belgium | F15: =IFERROR(SUMIF('Expense Tracker'!E12:E500,E15,'Expense Tracker'!H12:H500),0) -> 0 | G15: =IFERROR(F15/'Expense Tracker'!D6,0) -> 0
A16: Legal | B16: =IFERROR(SUMIF('Expense Tracker'!C12:C500,A16,'Expense Tracker'!H12:H500),0) -> 0 | C16: =IFERROR(B16/'Expense Tracker'!D6,0) -> 0 | E16: UK | F16: =IFERROR(SUMIF('Expense Tracker'!E12:E500,E16,'Expense Tracker'!H12:H500),0) -> 0 | G16: =IFERROR(F16/'Expense Tracker'!D6,0) -> 0
A17: Tax & Compliance | B17: =IFERROR(SUMIF('Expense Tracker'!C12:C500,A17,'Expense Tracker'!H12:H500),0) -> 238500 | C17: =IFERROR(B17/'Expense Tracker'!D6,0) -> 0.97410753 | E17: Other | F17: =IFERROR(SUMIF('Expense Tracker'!E12:E500,E17,'Expense Tracker'!H12:H500),0) -> 800 | G17: =IFERROR(F17/'Expense Tracker'!D6,0) -> 0.0032674466
A18: Other | B18: =IFERROR(SUMIF('Expense Tracker'!C12:C500,A18,'Expense Tracker'!H12:H500),0) -> 0 | C18: =IFERROR(B18/'Expense Tracker'!D6,0) -> 0
A22: HOW TO USE THIS WORKBOOK
A23: 1. VAT Calculator | B23: Enter net amounts & select region. Copy VAT amounts to Expense Tracker.
A24: 2. Expense Tracker | B24: Enter each expense. Pick category & country from dropdowns. Gross auto-calculates.
A25: 3. Dashboard | B25: All KPIs update automatically — no manual entry here.
A26: 4. Blue cells | B26: Input fields to edit. Black cells = auto-calculated formulas. Yellow = set your budget.
A27: 5. Export | B27: File → Export → PDF or CSV to send to accountant / tax authority.
